{
  "activePlaceCount": 1, 
  "activePlaces": [
    {
      "name": "Brooklyn, United States", 
      "placeName": "Brooklyn", 
      "placeType": "city"
    }
  ], 
  "birth": {
    "place": {
      "name": "Santa Monica, United States", 
      "placeName": "Santa Monica", 
      "placeType": "inhabited_place"
    }, 
    "time": {
      "startYear": 1962
    }
  }, 
  "birthYear": 1962, 
  "date": "born 1962", 
  "fc": "Fred Tomaselli", 
  "gender": "Male", 
  "id": 6854, 
  "mda": "Tomaselli, Fred", 
  "movements": [], 
  "startLetter": "T", 
  "totalWorks": 1, 
  "url": "http://www.tate.org.uk/art/artists/fred-tomaselli-6854"
}