{
  "activePlaceCount": 1, 
  "activePlaces": [
    {
      "name": "Great Britain, United Kingdom", 
      "placeName": "Great Britain", 
      "placeType": "island"
    }
  ], 
  "birth": {
    "place": {
      "name": "Ridgefield, United States", 
      "placeName": "Ridgefield", 
      "placeType": "inhabited_place"
    }, 
    "time": {
      "startYear": 1931
    }
  }, 
  "date": "born 1931", 
  "fc": "John Hubbard", 
  "gender": "Male", 
  "id": 1319, 
  "mda": "Hubbard, John", 
  "movements": [], 
  "popularity": 126, 
  "totalWorks": 5
}