{
  "activePlaceCount": 1, 
  "activePlaces": [
    {
      "name": "Paris, France", 
      "placeName": "Paris", 
      "placeType": "inhabited_place"
    }
  ], 
  "birth": {
    "place": {
      "name": "Paris, France", 
      "placeName": "Paris", 
      "placeType": "inhabited_place"
    }, 
    "time": {
      "startYear": 1962
    }
  }, 
  "birthYear": 1962, 
  "date": "born 1962", 
  "fc": "Pierre Huyghe", 
  "gender": "Male", 
  "id": 5463, 
  "mda": "Huyghe, Pierre", 
  "movements": [], 
  "startLetter": "H", 
  "totalWorks": 7, 
  "url": "http://www.tate.org.uk/art/artists/pierre-huyghe-5463"
}