{
  "activePlaceCount": 1, 
  "activePlaces": [
    {
      "name": "London, United Kingdom", 
      "placeName": "London", 
      "placeType": "inhabited_place"
    }
  ], 
  "birth": {
    "time": {
      "startYear": 1988
    }
  }, 
  "birthYear": 1988, 
  "date": "established 1988", 
  "fc": "City Racing (Matt Hale; Paul Noble, born 1963; John Burgess; Keith Coventry, born 1958; Peter Owen)", 
  "gender": "Male", 
  "id": 4599, 
  "mda": "City Racing (Matt Hale; Paul Noble, born 1963; John Burgess; Keith Coventry, born 1958; Peter Owen)", 
  "movements": [], 
  "startLetter": "C", 
  "totalWorks": 1, 
  "url": "http://www.tate.org.uk/art/artists/city-racing-matt-hale-paul-noble-born-1963-john-burgess-keith-coventry-born-1958-peter-4599"
}