{
  "activePlaceCount": 0, 
  "birth": {
    "place": {
      "name": "Lambeth, United Kingdom", 
      "placeName": "Lambeth", 
      "placeType": "unitary_authority"
    }, 
    "time": {
      "startYear": 1803
    }
  }, 
  "birthYear": 1803, 
  "date": "1803\u20131852", 
  "death": {
    "place": {
      "name": "London, United Kingdom", 
      "placeName": "London", 
      "placeType": "inhabited_place"
    }, 
    "time": {
      "startYear": 1852
    }
  }, 
  "fc": "Joseph William Allen", 
  "gender": "Male", 
  "id": 5, 
  "mda": "Allen, Joseph William", 
  "movements": [], 
  "startLetter": "A", 
  "totalWorks": 1, 
  "url": "http://www.tate.org.uk/art/artists/joseph-william-allen-5"
}