{
  "activePlaceCount": 0, 
  "birth": {
    "place": {
      "name": "Quincy, United States", 
      "placeName": "Quincy", 
      "placeType": "inhabited_place"
    }, 
    "time": {
      "startYear": 1935
    }
  }, 
  "birthYear": 1935, 
  "date": "born 1935", 
  "fc": "Carl Andre", 
  "gender": "Male", 
  "id": 648, 
  "mda": "Andre, Carl", 
  "movements": [
    {
      "era": {
        "id": 415, 
        "name": "20th century post-1945"
      }, 
      "id": 421, 
      "name": "Conceptual Art"
    }, 
    {
      "era": {
        "id": 415, 
        "name": "20th century post-1945"
      }, 
      "id": 430, 
      "name": "Minimalism"
    }
  ], 
  "startLetter": "A", 
  "totalWorks": 10, 
  "url": "http://www.tate.org.uk/art/artists/carl-andre-648"
}