{
  "activePlaceCount": 1, 
  "activePlaces": [
    {
      "name": "France", 
      "placeName": "France", 
      "placeType": "nation"
    }
  ], 
  "birth": {
    "place": {
      "name": "Sankt-Peterburg, Rossiya", 
      "placeName": "Sankt-Peterburg", 
      "placeType": "inhabited_place"
    }, 
    "time": {
      "startYear": 1887
    }
  }, 
  "birthYear": 1887, 
  "date": "1887\u20131938", 
  "death": {
    "place": {
      "name": "Paris, France", 
      "placeName": "Paris", 
      "placeType": "inhabited_place"
    }, 
    "time": {
      "startYear": 1938
    }
  }, 
  "fc": "Alexandre Jacovleff", 
  "gender": "Male", 
  "id": 1350, 
  "mda": "Jacovleff, Alexandre", 
  "movements": [], 
  "startLetter": "J", 
  "totalWorks": 12, 
  "url": "http://www.tate.org.uk/art/artists/alexandre-jacovleff-1350"
}