{
  "acno": "T02054", 
  "acquisitionYear": 1976, 
  "additionalImages": [
    {
      "copyright": "\u00a9 The Henry Moore Foundation; All rights reserved DACS 2014", 
      "creativeCommons": null, 
      "filenameBase": "T02054_324706", 
      "sizes": [
        {
          "caption": "Additional view 1", 
          "cleared": true, 
          "file": "T/T02/T02054_324706_7.jpg", 
          "height": 85, 
          "resolution": 128, 
          "size": "small", 
          "width": 128
        }, 
        {
          "caption": "Additional view 1", 
          "cleared": true, 
          "file": "T/T02/T02054_324706_8.jpg", 
          "height": 171, 
          "resolution": 256, 
          "size": "medium", 
          "width": 256
        }, 
        {
          "caption": "Additional view 1", 
          "cleared": true, 
          "file": "T/T02/T02054_324706_9.jpg", 
          "height": 488, 
          "resolution": 730, 
          "size": "large", 
          "width": 730
        }, 
        {
          "caption": "Additional view 1", 
          "cleared": true, 
          "file": "T/T02/T02054_324706_10.jpg", 
          "height": 1028, 
          "resolution": 1536, 
          "size": "optimal", 
          "width": 1536
        }
      ]
    }, 
    {
      "copyright": "\u00a9 The Henry Moore Foundation; All rights reserved DACS 2014", 
      "creativeCommons": null, 
      "filenameBase": "T02054_324708", 
      "sizes": [
        {
          "caption": "Additional view 2", 
          "cleared": true, 
          "file": "T/T02/T02054_324708_7.jpg", 
          "height": 128, 
          "resolution": 128, 
          "size": "small", 
          "width": 106
        }, 
        {
          "caption": "Additional view 2", 
          "cleared": true, 
          "file": "T/T02/T02054_324708_8.jpg", 
          "height": 256, 
          "resolution": 256, 
          "size": "medium", 
          "width": 213
        }, 
        {
          "caption": "Additional view 2", 
          "cleared": true, 
          "file": "T/T02/T02054_324708_9.jpg", 
          "height": 730, 
          "resolution": 730, 
          "size": "large", 
          "width": 607
        }, 
        {
          "caption": "Additional view 2", 
          "cleared": true, 
          "file": "T/T02/T02054_324708_10.jpg", 
          "height": 1536, 
          "resolution": 1536, 
          "size": "optimal", 
          "width": 1278
        }
      ]
    }, 
    {
      "copyright": "\u00a9 The Henry Moore Foundation; All rights reserved DACS 2014", 
      "creativeCommons": null, 
      "filenameBase": "T02054_324710", 
      "sizes": [
        {
          "caption": "Additional view 3", 
          "cleared": true, 
          "file": "T/T02/T02054_324710_7.jpg", 
          "height": 106, 
          "resolution": 128, 
          "size": "small", 
          "width": 128
        }, 
        {
          "caption": "Additional view 3", 
          "cleared": true, 
          "file": "T/T02/T02054_324710_8.jpg", 
          "height": 213, 
          "resolution": 256, 
          "size": "medium", 
          "width": 256
        }, 
        {
          "caption": "Additional view 3", 
          "cleared": true, 
          "file": "T/T02/T02054_324710_9.jpg", 
          "height": 609, 
          "resolution": 730, 
          "size": "large", 
          "width": 730
        }, 
        {
          "caption": "Additional view 3", 
          "cleared": true, 
          "file": "T/T02/T02054_324710_10.jpg", 
          "height": 1283, 
          "resolution": 1536, 
          "size": "optimal", 
          "width": 1536
        }
      ]
    }, 
    {
      "copyright": "\u00a9 The Henry Moore Foundation; All rights reserved DACS 2014", 
      "creativeCommons": null, 
      "filenameBase": "T02054_324712", 
      "sizes": [
        {
          "caption": "Additional view 4", 
          "cleared": true, 
          "file": "T/T02/T02054_324712_7.jpg", 
          "height": 88, 
          "resolution": 128, 
          "size": "small", 
          "width": 128
        }, 
        {
          "caption": "Additional view 4", 
          "cleared": true, 
          "file": "T/T02/T02054_324712_8.jpg", 
          "height": 177, 
          "resolution": 256, 
          "size": "medium", 
          "width": 256
        }, 
        {
          "caption": "Additional view 4", 
          "cleared": true, 
          "file": "T/T02/T02054_324712_9.jpg", 
          "height": 506, 
          "resolution": 730, 
          "size": "large", 
          "width": 730
        }, 
        {
          "caption": "Additional view 4", 
          "cleared": true, 
          "file": "T/T02/T02054_324712_10.jpg", 
          "height": 1066, 
          "resolution": 1536, 
          "size": "optimal", 
          "width": 1536
        }
      ]
    }, 
    {
      "copyright": "\u00a9 The Henry Moore Foundation; All rights reserved DACS 2014", 
      "creativeCommons": null, 
      "filenameBase": "T02054_324714", 
      "sizes": [
        {
          "caption": "Additional view 5", 
          "cleared": true, 
          "file": "T/T02/T02054_324714_7.jpg", 
          "height": 83, 
          "resolution": 128, 
          "size": "small", 
          "width": 128
        }, 
        {
          "caption": "Additional view 5", 
          "cleared": true, 
          "file": "T/T02/T02054_324714_8.jpg", 
          "height": 166, 
          "resolution": 256, 
          "size": "medium", 
          "width": 256
        }, 
        {
          "caption": "Additional view 5", 
          "cleared": true, 
          "file": "T/T02/T02054_324714_9.jpg", 
          "height": 475, 
          "resolution": 730, 
          "size": "large", 
          "width": 730
        }, 
        {
          "caption": "Additional view 5", 
          "cleared": true, 
          "file": "T/T02/T02054_324714_10.jpg", 
          "height": 1001, 
          "resolution": 1536, 
          "size": "optimal", 
          "width": 1536
        }
      ]
    }, 
    {
      "copyright": "\u00a9 The Henry Moore Foundation; All rights reserved DACS 2014", 
      "creativeCommons": null, 
      "filenameBase": "T02054_324716", 
      "sizes": [
        {
          "caption": "Additional View 6", 
          "cleared": true, 
          "file": "T/T02/T02054_324716_7.jpg", 
          "height": 86, 
          "resolution": 128, 
          "size": "small", 
          "width": 128
        }, 
        {
          "caption": "Additional View 6", 
          "cleared": true, 
          "file": "T/T02/T02054_324716_8.jpg", 
          "height": 173, 
          "resolution": 256, 
          "size": "medium", 
          "width": 256
        }, 
        {
          "caption": "Additional View 6", 
          "cleared": true, 
          "file": "T/T02/T02054_324716_9.jpg", 
          "height": 494, 
          "resolution": 730, 
          "size": "large", 
          "width": 730
        }, 
        {
          "caption": "Additional View 6", 
          "cleared": true, 
          "file": "T/T02/T02054_324716_10.jpg", 
          "height": 1041, 
          "resolution": 1536, 
          "size": "optimal", 
          "width": 1536
        }
      ]
    }, 
    {
      "copyright": "\u00a9 The Henry Moore Foundation; All rights reserved DACS 2014", 
      "creativeCommons": null, 
      "filenameBase": "T02054_324718", 
      "sizes": [
        {
          "caption": "Additional View 7", 
          "cleared": true, 
          "file": "T/T02/T02054_324718_7.jpg", 
          "height": 80, 
          "resolution": 128, 
          "size": "small", 
          "width": 128
        }, 
        {
          "caption": "Additional View 7", 
          "cleared": true, 
          "file": "T/T02/T02054_324718_8.jpg", 
          "height": 161, 
          "resolution": 256, 
          "size": "medium", 
          "width": 256
        }, 
        {
          "caption": "Additional View 7", 
          "cleared": true, 
          "file": "T/T02/T02054_324718_9.jpg", 
          "height": 460, 
          "resolution": 730, 
          "size": "large", 
          "width": 730
        }, 
        {
          "caption": "Additional View 7", 
          "cleared": true, 
          "file": "T/T02/T02054_324718_10.jpg", 
          "height": 969, 
          "resolution": 1536, 
          "size": "optimal", 
          "width": 1536
        }
      ]
    }, 
    {
      "copyright": "\u00a9 The Henry Moore Foundation; All rights reserved DACS 2014", 
      "creativeCommons": null, 
      "filenameBase": "T02054_324720", 
      "sizes": [
        {
          "caption": "Additional View 8", 
          "cleared": true, 
          "file": "T/T02/T02054_324720_7.jpg", 
          "height": 115, 
          "resolution": 128, 
          "size": "small", 
          "width": 128
        }, 
        {
          "caption": "Additional View 8", 
          "cleared": true, 
          "file": "T/T02/T02054_324720_8.jpg", 
          "height": 231, 
          "resolution": 256, 
          "size": "medium", 
          "width": 256
        }, 
        {
          "caption": "Additional View 8", 
          "cleared": true, 
          "file": "T/T02/T02054_324720_9.jpg", 
          "height": 660, 
          "resolution": 730, 
          "size": "large", 
          "width": 730
        }, 
        {
          "caption": "Additional View 8", 
          "cleared": true, 
          "file": "T/T02/T02054_324720_10.jpg", 
          "height": 1390, 
          "resolution": 1536, 
          "size": "optimal", 
          "width": 1536
        }
      ]
    }, 
    {
      "copyright": "\u00a9 The Henry Moore Foundation; All rights reserved DACS 2014", 
      "creativeCommons": null, 
      "filenameBase": "T02054_324722", 
      "sizes": [
        {
          "caption": "Additional View 10", 
          "cleared": true, 
          "file": "T/T02/T02054_324722_7.jpg", 
          "height": 94, 
          "resolution": 128, 
          "size": "small", 
          "width": 128
        }, 
        {
          "caption": "Additional View 10", 
          "cleared": true, 
          "file": "T/T02/T02054_324722_8.jpg", 
          "height": 187, 
          "resolution": 256, 
          "size": "medium", 
          "width": 256
        }, 
        {
          "caption": "Additional View 10", 
          "cleared": true, 
          "file": "T/T02/T02054_324722_9.jpg", 
          "height": 534, 
          "resolution": 730, 
          "size": "large", 
          "width": 730
        }, 
        {
          "caption": "Additional View 10", 
          "cleared": true, 
          "file": "T/T02/T02054_324722_10.jpg", 
          "height": 1124, 
          "resolution": 1536, 
          "size": "optimal", 
          "width": 1536
        }
      ]
    }, 
    {
      "copyright": "\u00a9 The Henry Moore Foundation; All rights reserved DACS 2014", 
      "creativeCommons": null, 
      "filenameBase": "T02054_324724", 
      "sizes": [
        {
          "caption": "Additional View 10", 
          "cleared": true, 
          "file": "T/T02/T02054_324724_7.jpg", 
          "height": 96, 
          "resolution": 128, 
          "size": "small", 
          "width": 128
        }, 
        {
          "caption": "Additional View 10", 
          "cleared": true, 
          "file": "T/T02/T02054_324724_8.jpg", 
          "height": 192, 
          "resolution": 256, 
          "size": "medium", 
          "width": 256
        }, 
        {
          "caption": "Additional View 10", 
          "cleared": true, 
          "file": "T/T02/T02054_324724_9.jpg", 
          "height": 549, 
          "resolution": 730, 
          "size": "large", 
          "width": 730
        }, 
        {
          "caption": "Additional View 10", 
          "cleared": true, 
          "file": "T/T02/T02054_324724_10.jpg", 
          "height": 1156, 
          "resolution": 1536, 
          "size": "optimal", 
          "width": 1536
        }
      ]
    }, 
    {
      "copyright": "\u00a9 The Henry Moore Foundation; All rights reserved DACS 2014", 
      "creativeCommons": null, 
      "filenameBase": "T02054_324726", 
      "sizes": [
        {
          "caption": "Additional View 9", 
          "cleared": true, 
          "file": "T/T02/T02054_324726_7.jpg", 
          "height": 93, 
          "resolution": 128, 
          "size": "small", 
          "width": 128
        }, 
        {
          "caption": "Additional View 9", 
          "cleared": true, 
          "file": "T/T02/T02054_324726_8.jpg", 
          "height": 187, 
          "resolution": 256, 
          "size": "medium", 
          "width": 256
        }, 
        {
          "caption": "Additional View 9", 
          "cleared": true, 
          "file": "T/T02/T02054_324726_9.jpg", 
          "height": 534, 
          "resolution": 730, 
          "size": "large", 
          "width": 730
        }, 
        {
          "caption": "Additional View 9", 
          "cleared": true, 
          "file": "T/T02/T02054_324726_10.jpg", 
          "height": 1124, 
          "resolution": 1536, 
          "size": "optimal", 
          "width": 1536
        }
      ]
    }, 
    {
      "copyright": "\u00a9 The Henry Moore Foundation; All rights reserved DACS 2014", 
      "creativeCommons": null, 
      "filenameBase": "T02054_324728", 
      "sizes": [
        {
          "caption": "Additional View 11", 
          "cleared": true, 
          "file": "T/T02/T02054_324728_7.jpg", 
          "height": 93, 
          "resolution": 128, 
          "size": "small", 
          "width": 128
        }, 
        {
          "caption": "Additional View 11", 
          "cleared": true, 
          "file": "T/T02/T02054_324728_8.jpg", 
          "height": 186, 
          "resolution": 256, 
          "size": "medium", 
          "width": 256
        }, 
        {
          "caption": "Additional View 11", 
          "cleared": true, 
          "file": "T/T02/T02054_324728_9.jpg", 
          "height": 531, 
          "resolution": 730, 
          "size": "large", 
          "width": 730
        }, 
        {
          "caption": "Additional View 11", 
          "cleared": true, 
          "file": "T/T02/T02054_324728_10.jpg", 
          "height": 1118, 
          "resolution": 1536, 
          "size": "optimal", 
          "width": 1536
        }
      ]
    }, 
    {
      "copyright": "\u00a9 The Henry Moore Foundation; All rights reserved DACS 2014", 
      "creativeCommons": null, 
      "filenameBase": "T02054_324730", 
      "sizes": [
        {
          "caption": "Additional View 12", 
          "cleared": true, 
          "file": "T/T02/T02054_324730_7.jpg", 
          "height": 81, 
          "resolution": 128, 
          "size": "small", 
          "width": 128
        }, 
        {
          "caption": "Additional View 12", 
          "cleared": true, 
          "file": "T/T02/T02054_324730_8.jpg", 
          "height": 163, 
          "resolution": 256, 
          "size": "medium", 
          "width": 256
        }, 
        {
          "caption": "Additional View 12", 
          "cleared": true, 
          "file": "T/T02/T02054_324730_9.jpg", 
          "height": 465, 
          "resolution": 730, 
          "size": "large", 
          "width": 730
        }, 
        {
          "caption": "Additional View 12", 
          "cleared": true, 
          "file": "T/T02/T02054_324730_10.jpg", 
          "height": 979, 
          "resolution": 1536, 
          "size": "optimal", 
          "width": 1536
        }
      ]
    }, 
    {
      "copyright": "\u00a9 The Henry Moore Foundation; All rights reserved DACS 2014", 
      "creativeCommons": null, 
      "filenameBase": "T02054_324732", 
      "sizes": [
        {
          "caption": "Additional View 13", 
          "cleared": true, 
          "file": "T/T02/T02054_324732_7.jpg", 
          "height": 99, 
          "resolution": 128, 
          "size": "small", 
          "width": 128
        }, 
        {
          "caption": "Additional View 13", 
          "cleared": true, 
          "file": "T/T02/T02054_324732_8.jpg", 
          "height": 198, 
          "resolution": 256, 
          "size": "medium", 
          "width": 256
        }, 
        {
          "caption": "Additional View 13", 
          "cleared": true, 
          "file": "T/T02/T02054_324732_9.jpg", 
          "height": 566, 
          "resolution": 730, 
          "size": "large", 
          "width": 730
        }, 
        {
          "caption": "Additional View 13", 
          "cleared": true, 
          "file": "T/T02/T02054_324732_10.jpg", 
          "height": 1192, 
          "resolution": 1536, 
          "size": "optimal", 
          "width": 1536
        }
      ]
    }, 
    {
      "copyright": "\u00a9 The Henry Moore Foundation; All rights reserved DACS 2014", 
      "creativeCommons": null, 
      "filenameBase": "T02054_324734", 
      "sizes": [
        {
          "caption": "Additional View 14", 
          "cleared": true, 
          "file": "T/T02/T02054_324734_7.jpg", 
          "height": 69, 
          "resolution": 128, 
          "size": "small", 
          "width": 128
        }, 
        {
          "caption": "Additional View 14", 
          "cleared": true, 
          "file": "T/T02/T02054_324734_8.jpg", 
          "height": 138, 
          "resolution": 256, 
          "size": "medium", 
          "width": 256
        }, 
        {
          "caption": "Additional View 14", 
          "cleared": true, 
          "file": "T/T02/T02054_324734_9.jpg", 
          "height": 393, 
          "resolution": 730, 
          "size": "large", 
          "width": 730
        }, 
        {
          "caption": "Additional View 14", 
          "cleared": true, 
          "file": "T/T02/T02054_324734_10.jpg", 
          "height": 829, 
          "resolution": 1536, 
          "size": "optimal", 
          "width": 1536
        }
      ]
    }
  ], 
  "all_artists": "Henry Moore OM, CH", 
  "catTextResId": 1146342, 
  "catalogueGroup": {}, 
  "classification": "sculpture", 
  "contributorCount": 1, 
  "contributors": [
    {
      "birthYear": 1898, 
      "date": "1898\u20131986", 
      "displayOrder": 1, 
      "fc": "Henry Moore OM, CH", 
      "gender": "Male", 
      "id": 1659, 
      "mda": "Moore, Henry, OM, CH", 
      "role": "artist", 
      "startLetter": "M"
    }
  ], 
  "creditLine": "Purchased with assistance from the Art Fund 1976", 
  "dateRange": {
    "endYear": 1934, 
    "startYear": 1934, 
    "text": "1934"
  }, 
  "dateText": "1934", 
  "depth": "203", 
  "dimensions": "object: 175 x 457 x 203 mm", 
  "foreignTitle": null, 
  "groupTitle": null, 
  "height": "457", 
  "id": 10238, 
  "inscription": null, 
  "medium": "Cumberland alabaster", 
  "movementCount": 2, 
  "movements": [
    {
      "era": {
        "id": 8, 
        "name": "20th century 1900-1945"
      }, 
      "id": 303, 
      "name": "Direct Carving"
    }, 
    {
      "era": {
        "id": 8, 
        "name": "20th century 1900-1945"
      }, 
      "id": 321, 
      "name": "Unit One"
    }
  ], 
  "subjectCount": 9, 
  "subjects": {
    "children": [
      {
        "children": [
          {
            "children": [
              {
                "id": 1596, 
                "name": "environment / nature"
              }
            ], 
            "id": 30, 
            "name": "universal concepts"
          }, 
          {
            "children": [
              {
                "id": 6919, 
                "name": "fragmentation"
              }
            ], 
            "id": 6729, 
            "name": "formal qualities"
          }
        ], 
        "id": 29, 
        "name": "emotions, concepts and ideas"
      }, 
      {
        "children": [
          {
            "children": [
              {
                "id": 636, 
                "name": "hill"
              }
            ], 
            "id": 71, 
            "name": "landscape"
          }, 
          {
            "children": [
              {
                "id": 13390, 
                "name": "stone"
              }
            ], 
            "id": 70, 
            "name": "natural phenomena"
          }
        ], 
        "id": 60, 
        "name": "nature"
      }, 
      {
        "children": [
          {
            "children": [
              {
                "id": 796, 
                "name": "irregular forms"
              }
            ], 
            "id": 185, 
            "name": "non-representational"
          }, 
          {
            "children": [
              {
                "id": 223, 
                "name": "landscape"
              }
            ], 
            "id": 189, 
            "name": "from recognisable sources"
          }
        ], 
        "id": 184, 
        "name": "abstraction"
      }, 
      {
        "children": [
          {
            "children": [
              {
                "id": 2915, 
                "name": "procreation"
              }
            ], 
            "id": 146, 
            "name": "birth to death"
          }
        ], 
        "id": 145, 
        "name": "society"
      }, 
      {
        "children": [
          {
            "children": [
              {
                "id": 565, 
                "name": "reclining"
              }
            ], 
            "id": 92, 
            "name": "actions: postures and motions"
          }, 
          {
            "children": [
              {
                "id": 167, 
                "name": "woman"
              }
            ], 
            "id": 95, 
            "name": "adults"
          }
        ], 
        "id": 91, 
        "name": "people"
      }
    ], 
    "id": 1, 
    "name": "subject"
  }, 
  "thumbnailCopyright": "\u00a9 The Henry Moore Foundation; All rights reserved DACS 2014", 
  "thumbnailUrl": "http://www.tate.org.uk/art/images/work/T/T02/T02054_8.jpg", 
  "title": "Four-Piece Composition: Reclining Figure", 
  "units": "mm", 
  "url": "http://www.tate.org.uk/art/artworks/moore-four-piece-composition-reclining-figure-t02054", 
  "width": "175"
}