{
  "activePlaceCount": 0, 
  "birth": {
    "place": {
      "name": "South Bend, United States", 
      "placeName": "South Bend", 
      "placeType": "inhabited_place"
    }, 
    "time": {
      "startYear": 1907
    }
  }, 
  "birthYear": 1907, 
  "date": "1907\u20132002", 
  "death": {
    "place": {
      "name": "East Chatham, United States", 
      "placeName": "East Chatham", 
      "placeType": "inhabited_place"
    }, 
    "time": {
      "startYear": 2002
    }
  }, 
  "fc": "George Rickey", 
  "gender": "Male", 
  "id": 1844, 
  "mda": "Rickey, George", 
  "movements": [], 
  "startLetter": "R", 
  "totalWorks": 2, 
  "url": "http://www.tate.org.uk/art/artists/george-rickey-1844"
}