{
  "activePlaceCount": 1, 
  "activePlaces": [
    {
      "name": "Cornwall, United Kingdom", 
      "placeName": "Cornwall", 
      "placeType": "county"
    }
  ], 
  "birth": {
    "place": {
      "name": "Deutschland", 
      "placeName": "Deutschland", 
      "placeType": "nation"
    }, 
    "time": {
      "startYear": 1925
    }
  }, 
  "date": "1925-2005", 
  "death": {
    "time": {
      "startYear": 2005
    }
  }, 
  "fc": "Karl Weschke", 
  "gender": "Male", 
  "id": 2133, 
  "mda": "Weschke, Karl", 
  "movements": [
    {
      "era": {
        "id": 415, 
        "name": "20th century post-1945", 
        "workCount": 3604
      }, 
      "id": 441, 
      "name": "St Ives School", 
      "workCount": 409
    }
  ], 
  "popularity": 152, 
  "totalWorks": 7
}