{
  "activePlaceCount": 0, 
  "birth": {
    "place": {
      "name": "Macclesfield, United Kingdom", 
      "placeName": "Macclesfield", 
      "placeType": "inhabited_place"
    }, 
    "time": {
      "startYear": 1968
    }
  }, 
  "birthYear": 1968, 
  "date": "born 1968", 
  "fc": "David Shrigley", 
  "gender": "Male", 
  "id": 10208, 
  "mda": "Shrigley, David", 
  "movements": [
    {
      "era": {
        "id": 415, 
        "name": "20th century post-1945"
      }, 
      "id": 16666, 
      "name": "Abject art"
    }
  ], 
  "startLetter": "S", 
  "totalWorks": 16, 
  "url": "http://www.tate.org.uk/art/artists/david-shrigley-10208"
}