{
  "activePlaceCount": 0, 
  "birth": {
    "place": {
      "name": "Sankt-Peterburg, Rossiya", 
      "placeName": "Sankt-Peterburg", 
      "placeType": "inhabited_place"
    }, 
    "time": {
      "startYear": 1914
    }
  }, 
  "date": "1914-1955", 
  "death": {
    "place": {
      "name": "Antibes, France", 
      "placeName": "Antibes", 
      "placeType": "inhabited_place"
    }, 
    "time": {
      "startYear": 1955
    }
  }, 
  "fc": "Nicolas de Stael", 
  "gender": "Male", 
  "id": 1982, 
  "mda": "Stael, Nicolas de", 
  "movements": [], 
  "popularity": 701, 
  "totalWorks": 3
}