{
  "activePlaceCount": 0, 
  "birth": {
    "place": {
      "name": "Paris, France", 
      "placeName": "Paris", 
      "placeType": "inhabited_place"
    }, 
    "time": {
      "startYear": 1908
    }
  }, 
  "date": "1908-2001", 
  "death": {
    "time": {
      "startYear": 2001
    }
  }, 
  "fc": "Balthus (Balthasar Klossowski de Rola)", 
  "gender": "Male", 
  "id": 689, 
  "mda": "Klossowski de Rola, Balthus", 
  "movements": [
    {
      "era": {
        "id": 8, 
        "name": "20th century 1900-1945", 
        "workCount": 1052
      }, 
      "id": 311, 
      "name": "Modern Realism", 
      "workCount": 4
    }
  ], 
  "popularity": 546, 
  "totalWorks": 3
}