{
  "activePlaceCount": 1, 
  "activePlaces": [
    {
      "name": "New York, United States", 
      "placeName": "New York", 
      "placeType": "inhabited_place"
    }
  ], 
  "birth": {
    "place": {
      "name": "Rotterdam, Nederland", 
      "placeName": "Rotterdam", 
      "placeType": "inhabited_place"
    }, 
    "time": {
      "startYear": 1904
    }
  }, 
  "birthYear": 1904, 
  "date": "1904\u20131997", 
  "death": {
    "place": {
      "name": "East Hampton, United States", 
      "placeName": "East Hampton", 
      "placeType": "inhabited_place"
    }, 
    "time": {
      "startYear": 1997
    }
  }, 
  "fc": "Willem de Kooning", 
  "gender": "Male", 
  "id": 1433, 
  "mda": "Kooning, Willem de", 
  "movements": [
    {
      "era": {
        "id": 415, 
        "name": "20th century post-1945"
      }, 
      "id": 416, 
      "name": "Abstract Expressionism"
    }
  ], 
  "startLetter": "K", 
  "totalWorks": 6, 
  "url": "http://www.tate.org.uk/art/artists/willem-de-kooning-1433"
}