{
  "acno": "N05387", 
  "acquisitionYear": 1939, 
  "additionalImages": [
    {
      "copyright": "\u00a9 The Henry Moore Foundation; All rights reserved DACS 2014", 
      "creativeCommons": null, 
      "filenameBase": "N05387_325192", 
      "sizes": [
        {
          "caption": "Additional view 1", 
          "cleared": true, 
          "file": "N/N05/N05387_325192_7.jpg", 
          "height": 128, 
          "resolution": 128, 
          "size": "small", 
          "width": 123
        }, 
        {
          "caption": "Additional view 1", 
          "cleared": true, 
          "file": "N/N05/N05387_325192_8.jpg", 
          "height": 256, 
          "resolution": 256, 
          "size": "medium", 
          "width": 246
        }, 
        {
          "caption": "Additional view 1", 
          "cleared": true, 
          "file": "N/N05/N05387_325192_9.jpg", 
          "height": 730, 
          "resolution": 730, 
          "size": "large", 
          "width": 703
        }, 
        {
          "caption": "Additional view 1", 
          "cleared": true, 
          "file": "N/N05/N05387_325192_10.jpg", 
          "height": 1536, 
          "resolution": 1536, 
          "size": "optimal", 
          "width": 1481
        }
      ]
    }, 
    {
      "copyright": "\u00a9 The Henry Moore Foundation; All rights reserved DACS 2014", 
      "creativeCommons": null, 
      "filenameBase": "N05387_325194", 
      "sizes": [
        {
          "caption": "Additional view 2", 
          "cleared": true, 
          "file": "N/N05/N05387_325194_7.jpg", 
          "height": 128, 
          "resolution": 128, 
          "size": "small", 
          "width": 91
        }, 
        {
          "caption": "Additional view 2", 
          "cleared": true, 
          "file": "N/N05/N05387_325194_8.jpg", 
          "height": 256, 
          "resolution": 256, 
          "size": "medium", 
          "width": 182
        }, 
        {
          "caption": "Additional view 2", 
          "cleared": true, 
          "file": "N/N05/N05387_325194_9.jpg", 
          "height": 730, 
          "resolution": 730, 
          "size": "large", 
          "width": 520
        }, 
        {
          "caption": "Additional view 2", 
          "cleared": true, 
          "file": "N/N05/N05387_325194_10.jpg", 
          "height": 1536, 
          "resolution": 1536, 
          "size": "optimal", 
          "width": 1096
        }
      ]
    }, 
    {
      "copyright": "\u00a9 The Henry Moore Foundation; All rights reserved DACS 2014", 
      "creativeCommons": null, 
      "filenameBase": "N05387_325196", 
      "sizes": [
        {
          "caption": "Additional view 3", 
          "cleared": true, 
          "file": "N/N05/N05387_325196_7.jpg", 
          "height": 107, 
          "resolution": 128, 
          "size": "small", 
          "width": 128
        }, 
        {
          "caption": "Additional view 3", 
          "cleared": true, 
          "file": "N/N05/N05387_325196_8.jpg", 
          "height": 214, 
          "resolution": 256, 
          "size": "medium", 
          "width": 256
        }, 
        {
          "caption": "Additional view 3", 
          "cleared": true, 
          "file": "N/N05/N05387_325196_9.jpg", 
          "height": 611, 
          "resolution": 730, 
          "size": "large", 
          "width": 730
        }, 
        {
          "caption": "Additional view 3", 
          "cleared": true, 
          "file": "N/N05/N05387_325196_10.jpg", 
          "height": 1286, 
          "resolution": 1536, 
          "size": "optimal", 
          "width": 1536
        }
      ]
    }, 
    {
      "copyright": "\u00a9 The Henry Moore Foundation; All rights reserved DACS 2014", 
      "creativeCommons": null, 
      "filenameBase": "N05387_325198", 
      "sizes": [
        {
          "caption": "Additional view 4", 
          "cleared": true, 
          "file": "N/N05/N05387_325198_7.jpg", 
          "height": 91, 
          "resolution": 128, 
          "size": "small", 
          "width": 128
        }, 
        {
          "caption": "Additional view 4", 
          "cleared": true, 
          "file": "N/N05/N05387_325198_8.jpg", 
          "height": 183, 
          "resolution": 256, 
          "size": "medium", 
          "width": 256
        }, 
        {
          "caption": "Additional view 4", 
          "cleared": true, 
          "file": "N/N05/N05387_325198_9.jpg", 
          "height": 522, 
          "resolution": 730, 
          "size": "large", 
          "width": 730
        }, 
        {
          "caption": "Additional view 4", 
          "cleared": true, 
          "file": "N/N05/N05387_325198_10.jpg", 
          "height": 1099, 
          "resolution": 1536, 
          "size": "optimal", 
          "width": 1536
        }
      ]
    }, 
    {
      "copyright": "\u00a9 The Henry Moore Foundation; All rights reserved DACS 2014", 
      "creativeCommons": null, 
      "filenameBase": "N05387_325200", 
      "sizes": [
        {
          "caption": "Additional view 5", 
          "cleared": true, 
          "file": "N/N05/N05387_325200_7.jpg", 
          "height": 123, 
          "resolution": 128, 
          "size": "small", 
          "width": 128
        }, 
        {
          "caption": "Additional view 5", 
          "cleared": true, 
          "file": "N/N05/N05387_325200_8.jpg", 
          "height": 246, 
          "resolution": 256, 
          "size": "medium", 
          "width": 256
        }, 
        {
          "caption": "Additional view 5", 
          "cleared": true, 
          "file": "N/N05/N05387_325200_9.jpg", 
          "height": 703, 
          "resolution": 730, 
          "size": "large", 
          "width": 730
        }, 
        {
          "caption": "Additional view 5", 
          "cleared": true, 
          "file": "N/N05/N05387_325200_10.jpg", 
          "height": 1481, 
          "resolution": 1536, 
          "size": "optimal", 
          "width": 1536
        }
      ]
    }, 
    {
      "copyright": "\u00a9 The Henry Moore Foundation; All rights reserved DACS 2014", 
      "creativeCommons": null, 
      "filenameBase": "N05387_325202", 
      "sizes": [
        {
          "caption": "Additional View 6", 
          "cleared": true, 
          "file": "N/N05/N05387_325202_7.jpg", 
          "height": 128, 
          "resolution": 128, 
          "size": "small", 
          "width": 120
        }, 
        {
          "caption": "Additional View 6", 
          "cleared": true, 
          "file": "N/N05/N05387_325202_8.jpg", 
          "height": 256, 
          "resolution": 256, 
          "size": "medium", 
          "width": 241
        }, 
        {
          "caption": "Additional View 6", 
          "cleared": true, 
          "file": "N/N05/N05387_325202_9.jpg", 
          "height": 730, 
          "resolution": 730, 
          "size": "large", 
          "width": 689
        }, 
        {
          "caption": "Additional View 6", 
          "cleared": true, 
          "file": "N/N05/N05387_325202_10.jpg", 
          "height": 1536, 
          "resolution": 1536, 
          "size": "optimal", 
          "width": 1450
        }
      ]
    }, 
    {
      "copyright": "\u00a9 The Henry Moore Foundation; All rights reserved DACS 2014", 
      "creativeCommons": null, 
      "filenameBase": "N05387_325204", 
      "sizes": [
        {
          "caption": "Additional View 7", 
          "cleared": true, 
          "file": "N/N05/N05387_325204_7.jpg", 
          "height": 120, 
          "resolution": 128, 
          "size": "small", 
          "width": 128
        }, 
        {
          "caption": "Additional View 7", 
          "cleared": true, 
          "file": "N/N05/N05387_325204_8.jpg", 
          "height": 240, 
          "resolution": 256, 
          "size": "medium", 
          "width": 256
        }, 
        {
          "caption": "Additional View 7", 
          "cleared": true, 
          "file": "N/N05/N05387_325204_9.jpg", 
          "height": 684, 
          "resolution": 730, 
          "size": "large", 
          "width": 730
        }, 
        {
          "caption": "Additional View 7", 
          "cleared": true, 
          "file": "N/N05/N05387_325204_10.jpg", 
          "height": 1440, 
          "resolution": 1536, 
          "size": "optimal", 
          "width": 1536
        }
      ]
    }, 
    {
      "copyright": "\u00a9 The Henry Moore Foundation; All rights reserved DACS 2014", 
      "creativeCommons": null, 
      "filenameBase": "N05387_325206", 
      "sizes": [
        {
          "caption": "Additional View 8", 
          "cleared": true, 
          "file": "N/N05/N05387_325206_7.jpg", 
          "height": 97, 
          "resolution": 128, 
          "size": "small", 
          "width": 128
        }, 
        {
          "caption": "Additional View 8", 
          "cleared": true, 
          "file": "N/N05/N05387_325206_8.jpg", 
          "height": 195, 
          "resolution": 256, 
          "size": "medium", 
          "width": 256
        }, 
        {
          "caption": "Additional View 8", 
          "cleared": true, 
          "file": "N/N05/N05387_325206_9.jpg", 
          "height": 557, 
          "resolution": 730, 
          "size": "large", 
          "width": 730
        }, 
        {
          "caption": "Additional View 8", 
          "cleared": true, 
          "file": "N/N05/N05387_325206_10.jpg", 
          "height": 1173, 
          "resolution": 1536, 
          "size": "optimal", 
          "width": 1536
        }
      ]
    }, 
    {
      "copyright": "\u00a9 The Henry Moore Foundation; All rights reserved DACS 2014", 
      "creativeCommons": null, 
      "filenameBase": "N05387_325208", 
      "sizes": [
        {
          "caption": "Additional View 9", 
          "cleared": true, 
          "file": "N/N05/N05387_325208_7.jpg", 
          "height": 115, 
          "resolution": 128, 
          "size": "small", 
          "width": 128
        }, 
        {
          "caption": "Additional View 9", 
          "cleared": true, 
          "file": "N/N05/N05387_325208_8.jpg", 
          "height": 231, 
          "resolution": 256, 
          "size": "medium", 
          "width": 256
        }, 
        {
          "caption": "Additional View 9", 
          "cleared": true, 
          "file": "N/N05/N05387_325208_9.jpg", 
          "height": 661, 
          "resolution": 730, 
          "size": "large", 
          "width": 730
        }, 
        {
          "caption": "Additional View 9", 
          "cleared": true, 
          "file": "N/N05/N05387_325208_10.jpg", 
          "height": 1391, 
          "resolution": 1536, 
          "size": "optimal", 
          "width": 1536
        }
      ]
    }, 
    {
      "copyright": "\u00a9 The Henry Moore Foundation; All rights reserved DACS 2014", 
      "creativeCommons": null, 
      "filenameBase": "N05387_325210", 
      "sizes": [
        {
          "caption": "Additional View 10", 
          "cleared": true, 
          "file": "N/N05/N05387_325210_7.jpg", 
          "height": 97, 
          "resolution": 128, 
          "size": "small", 
          "width": 128
        }, 
        {
          "caption": "Additional View 10", 
          "cleared": true, 
          "file": "N/N05/N05387_325210_8.jpg", 
          "height": 195, 
          "resolution": 256, 
          "size": "medium", 
          "width": 256
        }, 
        {
          "caption": "Additional View 10", 
          "cleared": true, 
          "file": "N/N05/N05387_325210_9.jpg", 
          "height": 556, 
          "resolution": 730, 
          "size": "large", 
          "width": 730
        }, 
        {
          "caption": "Additional View 10", 
          "cleared": true, 
          "file": "N/N05/N05387_325210_10.jpg", 
          "height": 1171, 
          "resolution": 1536, 
          "size": "optimal", 
          "width": 1536
        }
      ]
    }, 
    {
      "copyright": "\u00a9 The Henry Moore Foundation; All rights reserved DACS 2014", 
      "creativeCommons": null, 
      "filenameBase": "N05387_325212", 
      "sizes": [
        {
          "caption": "Additional View 11", 
          "cleared": true, 
          "file": "N/N05/N05387_325212_7.jpg", 
          "height": 93, 
          "resolution": 128, 
          "size": "small", 
          "width": 128
        }, 
        {
          "caption": "Additional View 11", 
          "cleared": true, 
          "file": "N/N05/N05387_325212_8.jpg", 
          "height": 186, 
          "resolution": 256, 
          "size": "medium", 
          "width": 256
        }, 
        {
          "caption": "Additional View 11", 
          "cleared": true, 
          "file": "N/N05/N05387_325212_9.jpg", 
          "height": 532, 
          "resolution": 730, 
          "size": "large", 
          "width": 730
        }, 
        {
          "caption": "Additional View 11", 
          "cleared": true, 
          "file": "N/N05/N05387_325212_10.jpg", 
          "height": 1121, 
          "resolution": 1536, 
          "size": "optimal", 
          "width": 1536
        }
      ]
    }, 
    {
      "copyright": "\u00a9 The Henry Moore Foundation; All rights reserved DACS 2014", 
      "creativeCommons": null, 
      "filenameBase": "N05387_325214", 
      "sizes": [
        {
          "caption": "Additional View 12", 
          "cleared": true, 
          "file": "N/N05/N05387_325214_7.jpg", 
          "height": 87, 
          "resolution": 128, 
          "size": "small", 
          "width": 128
        }, 
        {
          "caption": "Additional View 12", 
          "cleared": true, 
          "file": "N/N05/N05387_325214_8.jpg", 
          "height": 174, 
          "resolution": 256, 
          "size": "medium", 
          "width": 256
        }, 
        {
          "caption": "Additional View 12", 
          "cleared": true, 
          "file": "N/N05/N05387_325214_9.jpg", 
          "height": 496, 
          "resolution": 730, 
          "size": "large", 
          "width": 730
        }, 
        {
          "caption": "Additional View 12", 
          "cleared": true, 
          "file": "N/N05/N05387_325214_10.jpg", 
          "height": 1045, 
          "resolution": 1536, 
          "size": "optimal", 
          "width": 1536
        }
      ]
    }, 
    {
      "copyright": "\u00a9 The Henry Moore Foundation; All rights reserved DACS 2014", 
      "creativeCommons": null, 
      "filenameBase": "N05387_325216", 
      "sizes": [
        {
          "caption": "Additional View 13", 
          "cleared": true, 
          "file": "N/N05/N05387_325216_7.jpg", 
          "height": 93, 
          "resolution": 128, 
          "size": "small", 
          "width": 128
        }, 
        {
          "caption": "Additional View 13", 
          "cleared": true, 
          "file": "N/N05/N05387_325216_8.jpg", 
          "height": 186, 
          "resolution": 256, 
          "size": "medium", 
          "width": 256
        }, 
        {
          "caption": "Additional View 13", 
          "cleared": true, 
          "file": "N/N05/N05387_325216_9.jpg", 
          "height": 532, 
          "resolution": 730, 
          "size": "large", 
          "width": 730
        }, 
        {
          "caption": "Additional View 13", 
          "cleared": true, 
          "file": "N/N05/N05387_325216_10.jpg", 
          "height": 1121, 
          "resolution": 1536, 
          "size": "optimal", 
          "width": 1536
        }
      ]
    }, 
    {
      "copyright": "\u00a9 The Henry Moore Foundation; All rights reserved DACS 2014", 
      "creativeCommons": null, 
      "filenameBase": "N05387_325218", 
      "sizes": [
        {
          "caption": "Additional View 14", 
          "cleared": true, 
          "file": "N/N05/N05387_325218_7.jpg", 
          "height": 101, 
          "resolution": 128, 
          "size": "small", 
          "width": 128
        }, 
        {
          "caption": "Additional View 14", 
          "cleared": true, 
          "file": "N/N05/N05387_325218_8.jpg", 
          "height": 202, 
          "resolution": 256, 
          "size": "medium", 
          "width": 256
        }, 
        {
          "caption": "Additional View 14", 
          "cleared": true, 
          "file": "N/N05/N05387_325218_9.jpg", 
          "height": 577, 
          "resolution": 730, 
          "size": "large", 
          "width": 730
        }, 
        {
          "caption": "Additional View 14", 
          "cleared": true, 
          "file": "N/N05/N05387_325218_10.jpg", 
          "height": 1215, 
          "resolution": 1536, 
          "size": "optimal", 
          "width": 1536
        }
      ]
    }
  ], 
  "all_artists": "Henry Moore OM, CH", 
  "catTextResId": 1146327, 
  "catalogueGroup": {}, 
  "classification": "sculpture", 
  "contributorCount": 1, 
  "contributors": [
    {
      "birthYear": 1898, 
      "date": "1898\u20131986", 
      "displayOrder": 1, 
      "fc": "Henry Moore OM, CH", 
      "gender": "Male", 
      "id": 1659, 
      "mda": "Moore, Henry, OM, CH", 
      "role": "artist", 
      "startLetter": "M"
    }
  ], 
  "creditLine": "Presented by the Contemporary Art Society 1939", 
  "dateRange": {
    "endYear": 1938, 
    "startYear": 1938, 
    "text": "1938"
  }, 
  "dateText": "1938", 
  "depth": "737", 
  "dimensions": "object: 889 x 1327 x 737 mm, 520 kg", 
  "foreignTitle": null, 
  "groupTitle": null, 
  "height": "1327", 
  "id": 9663, 
  "inscription": null, 
  "medium": "Green Hornton stone", 
  "movementCount": 2, 
  "movements": [
    {
      "era": {
        "id": 8, 
        "name": "20th century 1900-1945"
      }, 
      "id": 303, 
      "name": "Direct Carving"
    }, 
    {
      "era": {
        "id": 8, 
        "name": "20th century 1900-1945"
      }, 
      "id": 321, 
      "name": "Unit One"
    }
  ], 
  "subjectCount": 4, 
  "subjects": {
    "children": [
      {
        "children": [
          {
            "children": [
              {
                "id": 1596, 
                "name": "environment / nature"
              }
            ], 
            "id": 30, 
            "name": "universal concepts"
          }
        ], 
        "id": 29, 
        "name": "emotions, concepts and ideas"
      }, 
      {
        "children": [
          {
            "children": [
              {
                "id": 451, 
                "name": "figure"
              }
            ], 
            "id": 95, 
            "name": "adults"
          }, 
          {
            "children": [
              {
                "id": 565, 
                "name": "reclining"
              }
            ], 
            "id": 92, 
            "name": "actions: postures and motions"
          }
        ], 
        "id": 91, 
        "name": "people"
      }, 
      {
        "children": [
          {
            "children": [
              {
                "id": 221, 
                "name": "figure"
              }
            ], 
            "id": 189, 
            "name": "from recognisable sources"
          }
        ], 
        "id": 184, 
        "name": "abstraction"
      }
    ], 
    "id": 1, 
    "name": "subject"
  }, 
  "thumbnailCopyright": "\u00a9 The Henry Moore Foundation; All rights reserved DACS 2014", 
  "thumbnailUrl": "http://www.tate.org.uk/art/images/work/N/N05/N05387_8.jpg", 
  "title": "Recumbent Figure", 
  "units": "mm", 
  "url": "http://www.tate.org.uk/art/artworks/moore-recumbent-figure-n05387", 
  "width": "889"
}