{
  "activePlaceCount": 0, 
  "birth": {
    "place": {
      "name": "Chatou, France", 
      "placeName": "Chatou", 
      "placeType": "inhabited_place"
    }, 
    "time": {
      "startYear": 1930
    }
  }, 
  "birthYear": 1930, 
  "date": "born 1930", 
  "fc": "Fr\u00e9d\u00e9ric Benrath", 
  "gender": "Male", 
  "id": 2240, 
  "mda": "Benrath, Fr\u00e9d\u00e9ric", 
  "movements": [], 
  "startLetter": "B", 
  "totalWorks": 1, 
  "url": "http://www.tate.org.uk/art/artists/frederic-benrath-2240"
}