{
  "activePlaceCount": 3, 
  "activePlaces": [
    {
      "name": "England, United Kingdom", 
      "placeName": "England", 
      "placeType": "country"
    }, 
    {
      "name": "Paris, France", 
      "placeName": "Paris", 
      "placeType": "inhabited_place"
    }, 
    {
      "name": "Bretagne, France", 
      "placeName": "Bretagne", 
      "placeType": "region"
    }
  ], 
  "birth": {
    "place": {
      "name": "Hove, United Kingdom", 
      "placeName": "Hove", 
      "placeType": "inhabited_place"
    }, 
    "time": {
      "startYear": 1865
    }
  }, 
  "birthYear": 1865, 
  "date": "1865\u20131925", 
  "death": {
    "place": {
      "name": "London, United Kingdom", 
      "placeName": "London", 
      "placeType": "inhabited_place"
    }, 
    "time": {
      "startYear": 1925
    }
  }, 
  "fc": "Robert Bevan", 
  "gender": "Male", 
  "id": 748, 
  "mda": "Bevan, Robert", 
  "movements": [
    {
      "era": {
        "id": 8, 
        "name": "20th century 1900-1945"
      }, 
      "id": 297, 
      "name": "Camden Town Group"
    }
  ], 
  "startLetter": "B", 
  "totalWorks": 7, 
  "url": "http://www.tate.org.uk/art/artists/robert-bevan-748"
}