{
  "activePlaceCount": 0, 
  "birth": {
    "place": {
      "name": "Adelaide, Australia", 
      "placeName": "Adelaide", 
      "placeType": "inhabited_place"
    }, 
    "time": {
      "startYear": 1883
    }
  }, 
  "birthYear": 1883, 
  "date": "1883\u20131960", 
  "death": {
    "place": {
      "name": "Salisbury, United Kingdom", 
      "placeName": "Salisbury", 
      "placeType": "inhabited_place"
    }, 
    "time": {
      "startYear": 1960
    }
  }, 
  "fc": "Henry Lamb", 
  "gender": "Male", 
  "id": 1456, 
  "mda": "Lamb, Henry", 
  "movements": [
    {
      "era": {
        "id": 8, 
        "name": "20th century 1900-1945"
      }, 
      "id": 10525, 
      "name": "British War Art"
    }
  ], 
  "startLetter": "L", 
  "totalWorks": 10, 
  "url": "http://www.tate.org.uk/art/artists/henry-lamb-1456"
}