{
  "activePlaceCount": 3, 
  "activePlaces": [
    {
      "name": "Paris, France", 
      "placeName": "Paris", 
      "placeType": "inhabited_place"
    }, 
    {
      "name": "New York, United States", 
      "placeName": "New York", 
      "placeType": "inhabited_place"
    }, 
    {
      "name": "Barcelona, Espa\u00f1a", 
      "placeName": "Barcelona", 
      "placeType": "inhabited_place"
    }
  ], 
  "birth": {
    "place": {
      "name": "Paris, France", 
      "placeName": "Paris", 
      "placeType": "inhabited_place"
    }, 
    "time": {
      "startYear": 1879
    }
  }, 
  "birthYear": 1879, 
  "date": "1879\u20131953", 
  "death": {
    "place": {
      "name": "Paris, France", 
      "placeName": "Paris", 
      "placeType": "inhabited_place"
    }, 
    "time": {
      "startYear": 1953
    }
  }, 
  "fc": "Francis Picabia", 
  "gender": "Male", 
  "id": 1766, 
  "mda": "Picabia, Francis", 
  "movements": [
    {
      "artistCount": 8, 
      "era": {
        "artistCount": 237, 
        "id": 8, 
        "name": "20th century 1900-1945", 
        "workCount": 1052
      }, 
      "id": 300, 
      "name": "Dada", 
      "workCount": 22
    }, 
    {
      "artistCount": 31, 
      "era": {
        "artistCount": 237, 
        "id": 8, 
        "name": "20th century 1900-1945", 
        "workCount": 1052
      }, 
      "id": 320, 
      "name": "Surrealism", 
      "workCount": 98
    }
  ], 
  "startLetter": "P", 
  "totalWorks": 6, 
  "url": "http://www.tate.org.uk/art/artists/francis-picabia-1766"
}