{
  "activePlaceCount": 0, 
  "birth": {
    "place": {
      "name": "London, United Kingdom", 
      "placeName": "London", 
      "placeType": "inhabited_place"
    }, 
    "time": {
      "startYear": 1730
    }
  }, 
  "date": "before 1730-1788", 
  "death": {
    "place": {
      "name": "Philadelphia, United States", 
      "placeName": "Philadelphia", 
      "placeType": "inhabited_place"
    }, 
    "time": {
      "startYear": 1788
    }
  }, 
  "fc": "Robert Edge Pine", 
  "gender": "Male", 
  "id": 2313, 
  "mda": "Pine, Robert Edge", 
  "movements": [], 
  "popularity": 27, 
  "totalWorks": 1
}