{
  "activePlaceCount": 0, 
  "birth": {
    "place": {
      "name": "Biella, Italia", 
      "placeName": "Biella", 
      "placeType": "inhabited_place"
    }, 
    "time": {
      "startYear": 1933
    }
  }, 
  "birthYear": 1933, 
  "date": "born 1933", 
  "fc": "Michelangelo Pistoletto", 
  "gender": "Male", 
  "id": 8669, 
  "mda": "Pistoletto, Michelangelo", 
  "movements": [], 
  "startLetter": "P", 
  "totalWorks": 7, 
  "url": "http://www.tate.org.uk/art/artists/michelangelo-pistoletto-8669"
}