{
  "acno": "T05839", 
  "acquisitionYear": 1990, 
  "additionalImages": [
    {
      "copyright": "\u00a9 DACS, 2014", 
      "creativeCommons": null, 
      "filenameBase": "T05839_150524", 
      "sizes": [
        {
          "caption": null, 
          "cleared": true, 
          "file": "T/T05/T05839_150524_7.jpg", 
          "height": 84, 
          "resolution": 128, 
          "size": "small", 
          "width": 128
        }, 
        {
          "caption": null, 
          "cleared": true, 
          "file": "T/T05/T05839_150524_8.jpg", 
          "height": 169, 
          "resolution": 256, 
          "size": "medium", 
          "width": 256
        }, 
        {
          "caption": null, 
          "cleared": true, 
          "file": "T/T05/T05839_150524_9.jpg", 
          "height": 337, 
          "resolution": 512, 
          "size": "large", 
          "width": 512
        }, 
        {
          "caption": null, 
          "cleared": true, 
          "file": "T/T05/T05839_150524_10.jpg", 
          "height": 1012, 
          "resolution": 1536, 
          "size": "optimal", 
          "width": 1536
        }
      ]
    }, 
    {
      "copyright": "\u00a9 DACS, 2014", 
      "creativeCommons": null, 
      "filenameBase": "T05839_150526", 
      "sizes": [
        {
          "caption": null, 
          "cleared": true, 
          "file": "T/T05/T05839_150526_7.jpg", 
          "height": 128, 
          "resolution": 128, 
          "size": "small", 
          "width": 104
        }, 
        {
          "caption": null, 
          "cleared": true, 
          "file": "T/T05/T05839_150526_8.jpg", 
          "height": 256, 
          "resolution": 256, 
          "size": "medium", 
          "width": 208
        }, 
        {
          "caption": null, 
          "cleared": true, 
          "file": "T/T05/T05839_150526_9.jpg", 
          "height": 512, 
          "resolution": 512, 
          "size": "large", 
          "width": 415
        }, 
        {
          "caption": null, 
          "cleared": true, 
          "file": "T/T05/T05839_150526_10.jpg", 
          "height": 1536, 
          "resolution": 1536, 
          "size": "optimal", 
          "width": 1245
        }
      ]
    }, 
    {
      "copyright": "\u00a9 DACS, 2014", 
      "creativeCommons": null, 
      "filenameBase": "T05839_150528", 
      "sizes": [
        {
          "caption": null, 
          "cleared": true, 
          "file": "T/T05/T05839_150528_7.jpg", 
          "height": 85, 
          "resolution": 128, 
          "size": "small", 
          "width": 128
        }, 
        {
          "caption": null, 
          "cleared": true, 
          "file": "T/T05/T05839_150528_8.jpg", 
          "height": 169, 
          "resolution": 256, 
          "size": "medium", 
          "width": 256
        }, 
        {
          "caption": null, 
          "cleared": true, 
          "file": "T/T05/T05839_150528_9.jpg", 
          "height": 338, 
          "resolution": 512, 
          "size": "large", 
          "width": 512
        }, 
        {
          "caption": null, 
          "cleared": true, 
          "file": "T/T05/T05839_150528_10.jpg", 
          "height": 1014, 
          "resolution": 1536, 
          "size": "optimal", 
          "width": 1536
        }
      ]
    }, 
    {
      "copyright": "\u00a9 DACS, 2014", 
      "creativeCommons": null, 
      "filenameBase": "T05839_150531", 
      "sizes": [
        {
          "caption": null, 
          "cleared": true, 
          "file": "T/T05/T05839_150531_7.jpg", 
          "height": 85, 
          "resolution": 128, 
          "size": "small", 
          "width": 128
        }, 
        {
          "caption": null, 
          "cleared": true, 
          "file": "T/T05/T05839_150531_8.jpg", 
          "height": 170, 
          "resolution": 256, 
          "size": "medium", 
          "width": 256
        }, 
        {
          "caption": null, 
          "cleared": true, 
          "file": "T/T05/T05839_150531_9.jpg", 
          "height": 340, 
          "resolution": 512, 
          "size": "large", 
          "width": 512
        }, 
        {
          "caption": null, 
          "cleared": true, 
          "file": "T/T05/T05839_150531_10.jpg", 
          "height": 1019, 
          "resolution": 1536, 
          "size": "optimal", 
          "width": 1536
        }
      ]
    }, 
    {
      "copyright": "\u00a9 DACS, 2014", 
      "creativeCommons": null, 
      "filenameBase": "T05839_150534", 
      "sizes": [
        {
          "caption": null, 
          "cleared": true, 
          "file": "T/T05/T05839_150534_7.jpg", 
          "height": 84, 
          "resolution": 128, 
          "size": "small", 
          "width": 128
        }, 
        {
          "caption": null, 
          "cleared": true, 
          "file": "T/T05/T05839_150534_8.jpg", 
          "height": 169, 
          "resolution": 256, 
          "size": "medium", 
          "width": 256
        }, 
        {
          "caption": null, 
          "cleared": true, 
          "file": "T/T05/T05839_150534_9.jpg", 
          "height": 337, 
          "resolution": 512, 
          "size": "large", 
          "width": 512
        }, 
        {
          "caption": null, 
          "cleared": true, 
          "file": "T/T05/T05839_150534_10.jpg", 
          "height": 1008, 
          "resolution": 1536, 
          "size": "optimal", 
          "width": 1530
        }
      ]
    }, 
    {
      "copyright": "\u00a9 DACS, 2014", 
      "creativeCommons": null, 
      "filenameBase": "T05839_150536", 
      "sizes": [
        {
          "caption": null, 
          "cleared": true, 
          "file": "T/T05/T05839_150536_7.jpg", 
          "height": 85, 
          "resolution": 128, 
          "size": "small", 
          "width": 128
        }, 
        {
          "caption": null, 
          "cleared": true, 
          "file": "T/T05/T05839_150536_8.jpg", 
          "height": 170, 
          "resolution": 256, 
          "size": "medium", 
          "width": 256
        }, 
        {
          "caption": null, 
          "cleared": true, 
          "file": "T/T05/T05839_150536_9.jpg", 
          "height": 340, 
          "resolution": 512, 
          "size": "large", 
          "width": 512
        }, 
        {
          "caption": null, 
          "cleared": true, 
          "file": "T/T05/T05839_150536_10.jpg", 
          "height": 1019, 
          "resolution": 1536, 
          "size": "optimal", 
          "width": 1534
        }
      ]
    }, 
    {
      "copyright": "\u00a9 DACS, 2014", 
      "creativeCommons": null, 
      "filenameBase": "T05839_150670", 
      "sizes": [
        {
          "caption": "Polyptych", 
          "cleared": true, 
          "file": "T/T05/T05839_150670_7.jpg", 
          "height": 85, 
          "resolution": 128, 
          "size": "small", 
          "width": 128
        }, 
        {
          "caption": "Polyptych", 
          "cleared": true, 
          "file": "T/T05/T05839_150670_8.jpg", 
          "height": 170, 
          "resolution": 256, 
          "size": "medium", 
          "width": 256
        }, 
        {
          "caption": "Polyptych", 
          "cleared": true, 
          "file": "T/T05/T05839_150670_9.jpg", 
          "height": 339, 
          "resolution": 512, 
          "size": "large", 
          "width": 512
        }, 
        {
          "caption": "Polyptych", 
          "cleared": true, 
          "file": "T/T05/T05839_150670_10.jpg", 
          "height": 1017, 
          "resolution": 1536, 
          "size": "optimal", 
          "width": 1536
        }
      ]
    }, 
    {
      "copyright": "\u00a9 DACS, 2014", 
      "creativeCommons": null, 
      "filenameBase": "T05839_150672", 
      "sizes": [
        {
          "caption": "Polyptych", 
          "cleared": true, 
          "file": "T/T05/T05839_150672_7.jpg", 
          "height": 85, 
          "resolution": 128, 
          "size": "small", 
          "width": 128
        }, 
        {
          "caption": "Polyptych", 
          "cleared": true, 
          "file": "T/T05/T05839_150672_8.jpg", 
          "height": 170, 
          "resolution": 256, 
          "size": "medium", 
          "width": 256
        }, 
        {
          "caption": "Polyptych", 
          "cleared": true, 
          "file": "T/T05/T05839_150672_9.jpg", 
          "height": 339, 
          "resolution": 512, 
          "size": "large", 
          "width": 512
        }, 
        {
          "caption": "Polyptych", 
          "cleared": true, 
          "file": "T/T05/T05839_150672_10.jpg", 
          "height": 1018, 
          "resolution": 1536, 
          "size": "optimal", 
          "width": 1536
        }
      ]
    }, 
    {
      "copyright": "\u00a9 DACS, 2014", 
      "creativeCommons": null, 
      "filenameBase": "T05839_150674", 
      "sizes": [
        {
          "caption": "Polyptych", 
          "cleared": true, 
          "file": "T/T05/T05839_150674_7.jpg", 
          "height": 86, 
          "resolution": 128, 
          "size": "small", 
          "width": 128
        }, 
        {
          "caption": "Polyptych", 
          "cleared": true, 
          "file": "T/T05/T05839_150674_8.jpg", 
          "height": 172, 
          "resolution": 256, 
          "size": "medium", 
          "width": 256
        }, 
        {
          "caption": "Polyptych", 
          "cleared": true, 
          "file": "T/T05/T05839_150674_9.jpg", 
          "height": 344, 
          "resolution": 512, 
          "size": "large", 
          "width": 512
        }, 
        {
          "caption": "Polyptych", 
          "cleared": true, 
          "file": "T/T05/T05839_150674_10.jpg", 
          "height": 1032, 
          "resolution": 1536, 
          "size": "optimal", 
          "width": 1536
        }
      ]
    }, 
    {
      "copyright": "\u00a9 DACS, 2014", 
      "creativeCommons": null, 
      "filenameBase": "T05839_150676", 
      "sizes": [
        {
          "caption": "Polyptych", 
          "cleared": true, 
          "file": "T/T05/T05839_150676_7.jpg", 
          "height": 85, 
          "resolution": 128, 
          "size": "small", 
          "width": 128
        }, 
        {
          "caption": "Polyptych", 
          "cleared": true, 
          "file": "T/T05/T05839_150676_8.jpg", 
          "height": 170, 
          "resolution": 256, 
          "size": "medium", 
          "width": 256
        }, 
        {
          "caption": "Polyptych", 
          "cleared": true, 
          "file": "T/T05/T05839_150676_9.jpg", 
          "height": 339, 
          "resolution": 512, 
          "size": "large", 
          "width": 512
        }, 
        {
          "caption": "Polyptych", 
          "cleared": true, 
          "file": "T/T05/T05839_150676_10.jpg", 
          "height": 1018, 
          "resolution": 1536, 
          "size": "optimal", 
          "width": 1536
        }
      ]
    }, 
    {
      "copyright": "\u00a9 DACS, 2014", 
      "creativeCommons": null, 
      "filenameBase": "T05839_150678", 
      "sizes": [
        {
          "caption": "Polyptych", 
          "cleared": true, 
          "file": "T/T05/T05839_150678_7.jpg", 
          "height": 85, 
          "resolution": 128, 
          "size": "small", 
          "width": 128
        }, 
        {
          "caption": "Polyptych", 
          "cleared": true, 
          "file": "T/T05/T05839_150678_8.jpg", 
          "height": 169, 
          "resolution": 256, 
          "size": "medium", 
          "width": 256
        }, 
        {
          "caption": "Polyptych", 
          "cleared": true, 
          "file": "T/T05/T05839_150678_9.jpg", 
          "height": 339, 
          "resolution": 512, 
          "size": "large", 
          "width": 512
        }, 
        {
          "caption": "Polyptych", 
          "cleared": true, 
          "file": "T/T05/T05839_150678_10.jpg", 
          "height": 1016, 
          "resolution": 1536, 
          "size": "optimal", 
          "width": 1536
        }
      ]
    }, 
    {
      "copyright": "\u00a9 DACS, 2014", 
      "creativeCommons": null, 
      "filenameBase": "T05839_150680", 
      "sizes": [
        {
          "caption": "Polyptych", 
          "cleared": true, 
          "file": "T/T05/T05839_150680_7.jpg", 
          "height": 85, 
          "resolution": 128, 
          "size": "small", 
          "width": 128
        }, 
        {
          "caption": "Polyptych", 
          "cleared": true, 
          "file": "T/T05/T05839_150680_8.jpg", 
          "height": 170, 
          "resolution": 256, 
          "size": "medium", 
          "width": 256
        }, 
        {
          "caption": "Polyptych", 
          "cleared": true, 
          "file": "T/T05/T05839_150680_9.jpg", 
          "height": 340, 
          "resolution": 512, 
          "size": "large", 
          "width": 512
        }, 
        {
          "caption": "Polyptych", 
          "cleared": true, 
          "file": "T/T05/T05839_150680_10.jpg", 
          "height": 1020, 
          "resolution": 1536, 
          "size": "optimal", 
          "width": 1536
        }
      ]
    }
  ], 
  "all_artists": "Lothar Baumgarten", 
  "catalogueGroup": {}, 
  "classification": "installation", 
  "contributorCount": 1, 
  "contributors": [
    {
      "birthYear": 1944, 
      "date": "born 1944", 
      "displayOrder": 1, 
      "fc": "Lothar Baumgarten", 
      "gender": "Male", 
      "id": 706, 
      "mda": "Baumgarten, Lothar", 
      "role": "artist", 
      "startLetter": "B"
    }
  ], 
  "creditLine": "Purchased with assistance from the American Fund for the Tate Gallery, courtesy of Edwin C. Cohen and Echoing Green 1990", 
  "dateRange": {
    "endYear": 1985, 
    "startYear": 1977, 
    "text": "1977-85"
  }, 
  "dateText": "1977\u201385", 
  "depth": "", 
  "dimensions": "displayed: 1955 x 19890 mm", 
  "foreignTitle": null, 
  "groupTitle": null, 
  "height": "19890", 
  "id": 19271, 
  "inscription": "date inscribed", 
  "medium": "14 photographs, black and white, on paper and painted wall texts", 
  "movementCount": 1, 
  "movements": [
    {
      "era": {
        "id": 415, 
        "name": "20th century post-1945"
      }, 
      "id": 422, 
      "name": "Environmental Art"
    }
  ], 
  "subjectCount": 5, 
  "subjects": {
    "children": [
      {
        "children": [
          {
            "children": [
              {
                "id": 7326, 
                "name": "America, South"
              }
            ], 
            "id": 108, 
            "name": "countries and continents"
          }, 
          {
            "children": [
              {
                "id": 16600, 
                "name": "Eldorado"
              }
            ], 
            "id": 110, 
            "name": "mythical, religious, fictional"
          }
        ], 
        "id": 106, 
        "name": "places"
      }, 
      {
        "children": [
          {
            "children": [
              {
                "id": 1715, 
                "name": "destruction"
              }
            ], 
            "id": 30, 
            "name": "universal concepts"
          }, 
          {
            "children": [
              {
                "id": 9328, 
                "name": "photographic"
              }
            ], 
            "id": 6729, 
            "name": "formal qualities"
          }
        ], 
        "id": 29, 
        "name": "emotions, concepts and ideas"
      }, 
      {
        "children": [
          {
            "children": [
              {
                "id": 1308, 
                "name": "ecology"
              }
            ], 
            "id": 158, 
            "name": "social comment"
          }
        ], 
        "id": 145, 
        "name": "society"
      }
    ], 
    "id": 1, 
    "name": "subject"
  }, 
  "thumbnailCopyright": "\u00a9 DACS, 2014", 
  "thumbnailUrl": "http://www.tate.org.uk/art/images/work/T/T05/T05839_8.jpg", 
  "title": "El Dorado - Gran Sabana", 
  "units": "mm", 
  "url": "http://www.tate.org.uk/art/artworks/baumgarten-el-dorado-gran-sabana-t05839", 
  "width": "1955"
}