{
  "activePlaceCount": 0, 
  "birth": {
    "place": {
      "name": "Surrey, United Kingdom", 
      "placeName": "Surrey", 
      "placeType": "county"
    }, 
    "time": {
      "startYear": 1907
    }
  }, 
  "birthYear": 1907, 
  "date": "1907\u20132005", 
  "death": {
    "place": {
      "name": "Kew, United Kingdom", 
      "placeName": "Kew", 
      "placeType": "neighbourhood"
    }, 
    "time": {
      "startYear": 2005
    }
  }, 
  "fc": "Phyllis Ginger", 
  "gender": "Female", 
  "id": 1174, 
  "mda": "Ginger, Phyllis", 
  "movements": [], 
  "startLetter": "G", 
  "totalWorks": 1, 
  "url": "http://www.tate.org.uk/art/artists/phyllis-ginger-1174"
}