{
  "activePlaceCount": 0, 
  "birth": {
    "place": {
      "name": "Edinburgh, United Kingdom", 
      "placeName": "Edinburgh", 
      "placeType": "inhabited_place"
    }, 
    "time": {
      "startYear": 1803
    }
  }, 
  "date": "1803-1878", 
  "death": {
    "place": {
      "name": "Leicestershire, United Kingdom", 
      "placeName": "Leicestershire", 
      "placeType": "county"
    }, 
    "time": {
      "startYear": 1878
    }
  }, 
  "fc": "Sir Francis Grant", 
  "gender": "Male", 
  "id": 2281, 
  "mda": "Grant, Sir Francis", 
  "movements": [], 
  "popularity": 37, 
  "totalWorks": 1
}